thumbtrail/__init__.py
thumbtrail/aesmanager.py
thumbtrail/cli.py
thumbtrail/cryptomanager.py
thumbtrail/hlsmanager.py
thumbtrail/scrubber.py
thumbtrail-1.0.0.dist-info/LICENSE.txt
thumbtrail-1.0.0.dist-info/METADATA
thumbtrail-1.0.0.dist-info/WHEEL
thumbtrail-1.0.0.dist-info/entry_points.txt
thumbtrail-1.0.0.dist-info/top_level.txt
thumbtrail-1.0.0.dist-info/RECORD
