Metadata-Version: 2.1
Name: thumbtrail
Version: 1.0.0
Summary: A tool for generating WebVTT files and thumbnails for video scrubbing with encryption and decryption support.
Home-page: https://github.com/yourusername/thumbtrail
Author: Sariya Ansari
Classifier: Programming Language :: Python :: 3
Classifier: License :: OSI Approved :: MIT License
Classifier: Operating System :: OS Independent
Requires-Python: >=3.8
License-File: LICENSE.txt
Requires-Dist: opencv-python>=4.10.0.84
Requires-Dist: Pillow>=10.4.0
Requires-Dist: pycryptodome>=3.21.0
Requires-Dist: numpy
